kdPythonAPIViewer/LICENSE
kdPythonAPIViewer/README.md
kdPythonAPIViewer/__init__.py
kdPythonAPIViewer/fileutil.py
kdPythonAPIViewer/kdPythonAPIViewer.py
kdPythonAPIViewer/kdPythonAPIViewer.ui
kdPythonAPIViewer/pydocc.py
kdPythonAPIViewer/setup.py
kdPythonAPIViewer/show_mainwin.py
kdPythonAPIViewer/show_mainwin.ui
kdPythonAPIViewer/doc/kdPythonAPIViewer_screenshot.png
kdPythonAPIViewer-1.0.5.dist-info/DESCRIPTION.rst
kdPythonAPIViewer-1.0.5.dist-info/METADATA
kdPythonAPIViewer-1.0.5.dist-info/RECORD
kdPythonAPIViewer-1.0.5.dist-info/WHEEL
kdPythonAPIViewer-1.0.5.dist-info/entry_points.txt
kdPythonAPIViewer-1.0.5.dist-info/metadata.json
kdPythonAPIViewer-1.0.5.dist-info/top_level.txt
